ConsTADs/ConsTADs_main.py
ConsTADs/GetConsTADs.py
ConsTADs/IdentifyBoundaryRegions.py
ConsTADs/PlotFunction.py
ConsTADs/Preprocess.py
ConsTADs/TadSeparationLandscape.py
ConsTADs/__init__.py
ConsTADs/source.py
constads-1.0.0.dist-info/METADATA
constads-1.0.0.dist-info/WHEEL
constads-1.0.0.dist-info/licenses/LICENSE
constads-1.0.0.dist-info/RECORD
