Metadata-Version: 2.1
Name: ConsTADs
Version: 1.0.0
Summary: Defining the separation landscape of topological domains for decoding consensus domain organization of 3D genome
Project-URL: Homepage, https://github.com/zhanglabtools/ConsTADs
Author-email: Dachang Dang <dangdachang@163.com>
License: MIT License
License-File: LICENSE
Classifier: License :: OSI Approved :: MIT License
Classifier: Operating System :: OS Independent
Classifier: Programming Language :: Python :: 3
Requires-Python: >=3.7
Requires-Dist: matplotlib>=3.5.0
Requires-Dist: numpy>=1.20.3
Requires-Dist: pandas>=1.3.5
Requires-Dist: scikit-learn>=1.0
Requires-Dist: scipy>=1.7.3
Requires-Dist: tqdm>=4.64.1
